scnx_soar_integration_sdk/__init__.py
scnx_soar_integration_sdk/__main__.py
template/__init__.py
template/cookiecutter.json
template/hooks/post_gen_project.py
template/{{cookiecutter.integration_id}}/.coveragerc
template/{{cookiecutter.integration_id}}/Makefile
template/{{cookiecutter.integration_id}}/__init__.py
template/{{cookiecutter.integration_id}}/integration_definition.json
template/{{cookiecutter.integration_id}}/integration_meta.json
template/{{cookiecutter.integration_id}}/integration_meta_schema.json
template/{{cookiecutter.integration_id}}/logo.svg
template/{{cookiecutter.integration_id}}/requirements.txt
template/{{cookiecutter.integration_id}}/app/__init__.py
template/{{cookiecutter.integration_id}}/app/{{cookiecutter.integration_id}}.py
template/{{cookiecutter.integration_id}}/app/model/request_body.py
template/{{cookiecutter.integration_id}}/app/model/response_body.py
template/{{cookiecutter.integration_id}}/tests/__init__.py
template/{{cookiecutter.integration_id}}/tests/test_{{cookiecutter.integration_id}}.py
scnx_soar_integration_sdk-0.1.dist-info/LICENSE
scnx_soar_integration_sdk-0.1.dist-info/METADATA
scnx_soar_integration_sdk-0.1.dist-info/WHEEL
scnx_soar_integration_sdk-0.1.dist-info/entry_points.txt
scnx_soar_integration_sdk-0.1.dist-info/top_level.txt
scnx_soar_integration_sdk-0.1.dist-info/zip-safe
scnx_soar_integration_sdk-0.1.dist-info/RECORD
